gccov/__init__.py
gccov/coverm.py
gccov/main.py
gccov/scatter.py
gccov/version
gccov/version.py
gccov/workflow.py
gccov-1.0.3.data/scripts/gccov
gccov-1.0.3.dist-info/LICENSE
gccov-1.0.3.dist-info/METADATA
gccov-1.0.3.dist-info/WHEEL
gccov-1.0.3.dist-info/top_level.txt
gccov-1.0.3.dist-info/RECORD
